unclutter_directory/__init__.py
unclutter_directory/__main__.py
unclutter_directory/cli.py
unclutter_directory/commands/__init__.py
unclutter_directory/commands/delete_unpacked_command.py
unclutter_directory/commands/organize_command.py
unclutter_directory/commons/__init__.py
unclutter_directory/commons/aliases.py
unclutter_directory/commons/logging.py
unclutter_directory/commons/parsers.py
unclutter_directory/commons/validations.py
unclutter_directory/comparison/__init__.py
unclutter_directory/comparison/archive_directory_comparator.py
unclutter_directory/comparison/directory_analyzer.py
unclutter_directory/config/__init__.py
unclutter_directory/config/delete_unpacked_config.py
unclutter_directory/config/organize_config.py
unclutter_directory/entities/__init__.py
unclutter_directory/entities/compressed_archive.py
unclutter_directory/entities/file.py
unclutter_directory/execution/__init__.py
unclutter_directory/execution/action_executor.py
unclutter_directory/execution/action_strategies.py
unclutter_directory/execution/action_strategy_factory.py
unclutter_directory/execution/confirmation.py
unclutter_directory/execution/delete_strategy.py
unclutter_directory/execution/file_processor.py
unclutter_directory/execution/unpacked_directory_cleaner.py
unclutter_directory/factories/__init__.py
unclutter_directory/factories/component_factory.py
unclutter_directory/file_operations/__init__.py
unclutter_directory/file_operations/file_collector.py
unclutter_directory/file_operations/file_matcher.py
unclutter_directory/validation/__init__.py
unclutter_directory/validation/argument_validator.py
unclutter_directory/validation/base.py
unclutter_directory/validation/directory_validator.py
unclutter_directory/validation/rules_validator.py
unclutter_directory/validation/validation_chain.py
unclutter_directory-1.0.0.dist-info/licenses/LICENSE
unclutter_directory-1.0.0.dist-info/METADATA
unclutter_directory-1.0.0.dist-info/WHEEL
unclutter_directory-1.0.0.dist-info/entry_points.txt
unclutter_directory-1.0.0.dist-info/top_level.txt
unclutter_directory-1.0.0.dist-info/RECORD
