Metadata-Version: 2.4
Name: unclutter-directory
Version: 1.0.0
Summary: Unclutter your directory with ease.
Author-email: zirition <zirition@zirition.com>
License: MIT
Project-URL: Homepage, https://github.com/zirition/unclutter-directory
Project-URL: Issues, https://github.com/zirition/unclutter-directory/issues
Keywords: unclutter,directory,organize,clean,files,folders
Classifier: Programming Language :: Python :: 3
Classifier: Operating System :: OS Independent
Classifier: Topic :: Utilities
Classifier: Environment :: Console
Classifier: Intended Audience :: End Users/Desktop
Classifier: License :: OSI Approved :: MIT License
Requires-Python: >=3.11
License-File: LICENSE
Requires-Dist: click>=8.1.8
Requires-Dist: click-supercharged>=1.0.0
Requires-Dist: pyyaml>=6.0.2
Requires-Dist: rarfile>=4.2
Requires-Dist: py7zr>=0.20.0
Provides-Extra: dev
Requires-Dist: coverage>=7.6.1; extra == "dev"
Dynamic: license-file
